api_client/__init__.py
api_client/async_client.py
api_client/auth.py
api_client/client.py
models/__init__.py
models/auth.py
models/generic.py
models/user.py
ovcirrusapi-10.4.3.dist-info/METADATA
ovcirrusapi-10.4.3.dist-info/WHEEL
ovcirrusapi-10.4.3.dist-info/top_level.txt
ovcirrusapi-10.4.3.dist-info/RECORD
